pydocstruct/__init__.py
pydocstruct/__version__.py
pydocstruct/core/__init__.py
pydocstruct/core/chunker.py
pydocstruct/core/document.py
pydocstruct/core/loader.py
pydocstruct/loaders/__init__.py
pydocstruct/loaders/csv_loader.py
pydocstruct/loaders/docx_loader.py
pydocstruct/loaders/excel_loader.py
pydocstruct/loaders/html_loader.py
pydocstruct/loaders/json_loader.py
pydocstruct/loaders/markdown_loader.py
pydocstruct/loaders/pdf_loader.py
pydocstruct/loaders/text_loader.py
pydocstruct/loaders/xml_loader.py
pydocstruct/processors/__init__.py
pydocstruct/processors/html_cleaner.py
pydocstruct/processors/metadata_extractor.py
pydocstruct/processors/pii_redactor.py
pydocstruct/processors/text_cleaner.py
pydocstruct/utils/__init__.py
pydocstruct/utils/file_utils.py
pydocstruct-0.1.6.dist-info/METADATA
pydocstruct-0.1.6.dist-info/WHEEL
pydocstruct-0.1.6.dist-info/top_level.txt
pydocstruct-0.1.6.dist-info/RECORD
