Metadata-Version: 2.4
Name: pydocstruct
Version: 0.1.6
Summary: Document structuring library for RAG and vector databases
Home-page: https://github.com/shintaro-amaike/pydocstruct
Author: Shintaro Amaike
Author-email: Your Name <your.email@example.com>
License: MIT
Project-URL: Homepage, https://github.com/shintaro-amaike/pydocstruct
Project-URL: Documentation, https://docstruct.readthedocs.io
Project-URL: Repository, https://github.com/shintaro-amaike/pydocstruct
Project-URL: Bug Tracker, https://github.com/shintaro-amaike/pydocstruct/issues
Keywords: rag,document,vector,embedding,nlp
Classifier: Development Status :: 3 - Alpha
Classifier: Intended Audience :: Developers
Classifier: Topic :: Software Development :: Libraries :: Python Modules
Classifier: License :: OSI Approved :: MIT License
Classifier: Programming Language :: Python :: 3
Requires-Python: >=3.9
Requires-Dist: pypdf>=3.0.0
Requires-Dist: python-docx>=1.0.0
Requires-Dist: beautifulsoup4>=4.12.0
Requires-Dist: lxml>=4.9.0
Requires-Dist: markdown>=3.5.0
Provides-Extra: dev
Requires-Dist: pytest>=7.4.0; extra == "dev"
Requires-Dist: pytest-cov>=4.1.0; extra == "dev"
Requires-Dist: black>=23.0.0; extra == "dev"
Requires-Dist: flake8>=6.0.0; extra == "dev"
Requires-Dist: mypy>=1.5.0; extra == "dev"
Requires-Dist: isort>=5.12.0; extra == "dev"
Provides-Extra: all
Requires-Dist: openpyxl>=3.1.0; extra == "all"
Requires-Dist: pandas>=2.0.0; extra == "all"
Requires-Dist: tabulate>=0.9.0; extra == "all"
Requires-Dist: markdownify>=0.11.0; extra == "all"
Requires-Dist: tiktoken>=0.5.0; extra == "all"
Requires-Dist: pdf2image>=1.16.0; extra == "all"
Requires-Dist: pytesseract>=0.3.10; extra == "all"
Dynamic: author
Dynamic: home-page
Dynamic: requires-python
